{
  "fact_check_metadata": {
    "checked_at": "2026-03-15T16:00:00",
    "total_claims": 3,
    "verified": 2,
    "adjusted": 1,
    "unverified": 0,
    "disputed": 0
  },
  "checks": [
    {
      "claim_id": "FC-001",
      "location": "path_a > probability",
      "original_value": "公務員継続→管理職昇進",
      "original_note": "",
      "status": "verified",
      "verified_value": "妥当",
      "sources": [
        {
          "title": "調査データ",
          "url": "",
          "excerpt": "地方行政業界のデータと整合",
          "reliability": "medium"
        }
      ],
      "note": "地方行政業界のデータと整合",
      "suggested_correction": null
    },
    {
      "claim_id": "FC-002",
      "location": "path_b > income",
      "original_value": "700",
      "original_note": "",
      "status": "adjusted",
      "verified_value": "630-700",
      "sources": [
        {
          "title": "調査データ",
          "url": "",
          "excerpt": "市場データに基づき微調整",
          "reliability": "medium"
        }
      ],
      "note": "市場データに基づき微調整",
      "suggested_correction": {
        "value": "630-700",
        "note_addition": "市場データに基づき微調整"
      }
    },
    {
      "claim_id": "FC-003",
      "location": "overall > salary",
      "original_value": "520",
      "original_note": "",
      "status": "verified",
      "verified_value": "520",
      "sources": [
        {
          "title": "調査データ",
          "url": "",
          "excerpt": "新潟県庁の報酬水準と整合",
          "reliability": "medium"
        }
      ],
      "note": "新潟県庁の報酬水準と整合",
      "suggested_correction": null
    }
  ]
}